{"is_source_file": true, "format": "Python", "description": "Defines the AccountService class, inheriting from CRUDService with Account-related models, and instantiates it.", "external_files": ["src/db/models", "src.schemas.accounts", "src.services.common"], "external_methods": [], "published": ["account_service"], "classes": [{"name": "AccountService", "description": "A CRUD service class for Account model, extending generic CRUDService with specific Account schemas."}], "methods": [{"name": "AccountService", "description": "Constructor inheriting from CRUDService, initialized with the Account model."}], "calls": ["CRUDService[Account, AccountCreate, AccountUpdate]"], "search-terms": ["AccountService", "CRUDService", "accounts.py", "AccountCreate", "AccountUpdate"], "state": 2, "file_id": 14, "knowledge_revision": 61, "git_revision": "", "revision_history": [{"31": ""}, {"61": ""}], "ctags": [{"_type": "tag", "name": "AccountService", "path": "/home/kavia/workspace/code-generation/kavia-ai-crm-platform-87080-87094/crm_backend/src/services/accounts.py", "pattern": "/^class AccountService(CRUDService[Account, AccountCreate, AccountUpdate]):$/", "language": "Python", "kind": "class"}, {"_type": "tag", "name": "account_service", "path": "/home/kavia/workspace/code-generation/kavia-ai-crm-platform-87080-87094/crm_backend/src/services/accounts.py", "pattern": "/^account_service = AccountService(Account)$/", "language": "Python", "kind": "variable"}], "hash": "cd2cc5b8593e42871039a57c9611d632", "format-version": 4, "code-base-name": "crm_backend", "filename": "crm_backend/src/services/accounts.py", "fields": [{"name": "account_service = AccountService(Account)", "scope": "", "scopeKind": "", "description": "unavailable"}]}